pyinstrument_patch/__init__.py
pyinstrument_patch/profiler.py
pyinstrument_patch/session.py
pyinstrument_patch-0.0.2.dist-info/METADATA
pyinstrument_patch-0.0.2.dist-info/WHEEL
pyinstrument_patch-0.0.2.dist-info/top_level.txt
pyinstrument_patch-0.0.2.dist-info/RECORD
